{
  "version": 2,
  "sourcePath": "/Users/work-0110/Desktop/skill-reader-copy/skill/论文/jl00447.md",
  "updatedAt": "2026-03-17T14:11:06.485Z",
  "blocks": {
    "text-85d64172c4f2fd59": {
      "text": "# Skill jl00447 · 简介段落解读\n\n**核心作用**\n本段系统梳理了以索洛模型为起点的新古典增长理论与内生增长理论的演进脉络，将内生增长模型归纳为非递减报酬、内生技术进步、内生人口增长与劳动供给三种类型并逐一阐释。\n\n**重要性**\n该内容构建了理解现代经济增长理论的完整框架，明确指出索洛模型三个外生变量（储蓄率、技术进步率、人口增长率）的内生化方向，是掌握内生增长理论体系的核心入口。\n\n**关键点**\n需注意三类模型的发展成熟度差异显著：第一类（非递减报酬）已成宏观研究标准工具但并非严格意义上的内生增长模型，第二类（内生技术进步）是文献重点，第三类（内生人口）研究仍相对匮乏，使用时应避免混同对待。",
      "heading": "简介",
      "type": "text",
      "updatedAt": "2026-03-17T14:11:06.485Z"
    }
  }
}